Metadata-Version: 1.1
Name: django-tinymce-lite
Version: 0.0.1
Summary: A Django application that contains a widget to render a form field as a TinyMCE editor.
Home-page: https://github.com/vanadium23/django-tinymce-lite
Author: Ivan Chernov
Author-email: chernoffivan@gmail.com
License: MIT License
Keywords: django widget tinymce
Platform: any
Classifier: Development Status :: 5 - Production/Stable
Classifier: Environment :: Web Environment
Classifier: Framework :: Django
Classifier: Intended Audience :: Developers
Classifier: License :: OSI Approved :: MIT License
Classifier: Operating System :: OS Independent
Classifier: Programming Language :: Python
Classifier: Programming Language :: Python :: 2
Classifier: Programming Language :: Python :: 2.7
Classifier: Programming Language :: Python :: 3
Classifier: Programming Language :: Python :: 3.4
Classifier: Programming Language :: Python :: 3.5
Classifier: Topic :: Software Development :: Libraries :: Application Frameworks
Classifier: Topic :: Software Development :: Libraries :: Python Modules
